README.txt
setup.py
Products/__init__.py
Products/__init__.pyc
Products.CMFQuestionnaire.egg-info/PKG-INFO
Products.CMFQuestionnaire.egg-info/SOURCES.txt
Products.CMFQuestionnaire.egg-info/dependency_links.txt
Products.CMFQuestionnaire.egg-info/entry_points.txt
Products.CMFQuestionnaire.egg-info/namespace_packages.txt
Products.CMFQuestionnaire.egg-info/not-zip-safe
Products.CMFQuestionnaire.egg-info/requires.txt
Products.CMFQuestionnaire.egg-info/top_level.txt
Products/CMFQuestionnaire/Questionnaire.py
Products/CMFQuestionnaire/__init__.py
Products/CMFQuestionnaire/config.py
Products/CMFQuestionnaire/configure.zcml
Products/CMFQuestionnaire/permissions.py
Products/CMFQuestionnaire/refresh.txt
Products/CMFQuestionnaire/version.txt
Products/CMFQuestionnaire/i18n/cmfquestionnaire-es.po
Products/CMFQuestionnaire/i18n/cmfquestionnaire-tr.po
Products/CMFQuestionnaire/i18n/cmfquestionnaire.pot
Products/CMFQuestionnaire/i18n/plone-tr.po
Products/CMFQuestionnaire/i18n/plone.pot
Products/CMFQuestionnaire/profiles/default/cssregistry.xml
Products/CMFQuestionnaire/profiles/default/factorytool.xml
Products/CMFQuestionnaire/profiles/default/skins.xml
Products/CMFQuestionnaire/profiles/default/types.xml
Products/CMFQuestionnaire/profiles/default/types/Questionnaire.xml
Products/CMFQuestionnaire/skins/questionnaire/cmfquestionnaire.css
Products/CMFQuestionnaire/skins/questionnaire/dump.csv.cpy
Products/CMFQuestionnaire/skins/questionnaire/dump.xls.cpy
Products/CMFQuestionnaire/skins/questionnaire/dump.xml.cpy
Products/CMFQuestionnaire/skins/questionnaire/questionnaire.gif
Products/CMFQuestionnaire/skins/questionnaire/questionnaire_design.cpy
Products/CMFQuestionnaire/skins/questionnaire/questionnaire_design_form.cpt
Products/CMFQuestionnaire/skins/questionnaire/questionnaire_design_form.cpt.metadata
Products/CMFQuestionnaire/skins/questionnaire/questionnaire_fillout.cpy
Products/CMFQuestionnaire/skins/questionnaire/questionnaire_form_delete.cpy
Products/CMFQuestionnaire/skins/questionnaire/questionnaire_group_form.cpt
Products/CMFQuestionnaire/skins/questionnaire/questionnaire_group_form.cpt.metadata
Products/CMFQuestionnaire/skins/questionnaire/questionnaire_groups_manage.cpy
Products/CMFQuestionnaire/skins/questionnaire/questionnaire_question_form.cpt
Products/CMFQuestionnaire/skins/questionnaire/questionnaire_question_form.cpt.metadata
