Metadata-Version: 1.0
Name: Products.CMFQuestionnaire
Version: 0.6.2
Summary: A simple questionnaire for Plone.
Home-page: http://plone.org/products/cmfquestionnaire
Author: H. Turgut Uyar
Author-email: uyar@tekir.org
License: GPL
Keywords: Plone,questionnaire
Platform: UNKNOWN
Classifier: Programming Language :: Python
Classifier: Topic :: Software Development :: Libraries :: Python Modules
